lpp_parser/__init__.py
lpp_parser/_reg_map.py
lpp_parser/lppParser.py
lpp_parser/data/__init__.py
lpp_parser/data/sym_name_map.json
lpp_parser/data/sym_z_map.json
lpp_parser/tests/__init__.py
lpp_parser/tests/test_parser.py
lpp_parser/tests/test_utils.py
lpp_parser/tests/lppfiles/238U-190MeV-12C280mg-Alo85mm-223Th.lpp
lpp_parser/tests/lppfiles/44S_target8mm.lpp
lpp_parser/tests/lppfiles/SetB.65.00-1H_E262_C15mm_36Ar__c_aris__PSv05_KFv3.5.0__CB1s-R4003.lpp
lppParser-0.0.8.dist-info/LICENSE
lppParser-0.0.8.dist-info/METADATA
lppParser-0.0.8.dist-info/WHEEL
lppParser-0.0.8.dist-info/top_level.txt
lppParser-0.0.8.dist-info/RECORD
